naivepyrunner/__init__.py
naivepyrunner/job.py
naivepyrunner/queue.py
naivepyrunner/queuetransposer.py
naivepyrunner/runner.py
naivepyrunner/task.py
naivepyrunner/worker.py
naivepyrunner-0.2.0.dist-info/METADATA
naivepyrunner-0.2.0.dist-info/RECORD
naivepyrunner-0.2.0.dist-info/WHEEL
naivepyrunner-0.2.0.dist-info/top_level.txt
