Metadata-Version: 2.1
Name: naivepyrunner
Version: 0.2.0
Summary: Naive timed execution of custom handlers in multiple threads
Home-page: http://github.com/henningjanssen/naivepyrunner
Author: Henning Janßen
Author-email: development@henning-janssen.net
License: MIT
Keywords: schedule scheduling cron timing parallel
Platform: UNKNOWN
Classifier: Development Status :: 7 - Inactive
Classifier: License :: OSI Approved :: MIT License
Classifier: Programming Language :: Python :: 3.5
Classifier: Topic :: Utilities
Requires-Python: >=3.5
